extraction/__init__.py
extraction/core/__init__.py
extraction/core/extractor.py
extraction/core/functions/__init__.py
extraction/core/functions/cell.py
extraction/core/functions/custom/__init__.py
extraction/core/functions/custom/localisation.py
extraction/core/functions/defaults.py
extraction/core/functions/distributors.py
extraction/core/functions/io.py
extraction/core/functions/loaders.py
extraction/core/functions/math.py
extraction/core/functions/trap.py
extraction/core/functions/utils.py
extraction/core/functions/versioning.py
extraction/core/lineage.py
extraction/core/omero.py
extraction/core/tracks.py
extraction/examples/argo.py
extraction/examples/data.py
extraction/examples/pairs_data/pos010_trap001_tp0001_Brightfield.png
extraction/examples/pairs_data/pos010_trap001_tp0001_GFP.png
extraction/examples/pairs_data/pos010_trap001_tp0001_segoutlines.png
extraction/examples/pairs_data/pos010_trap050_tp0001_Brightfield.png
extraction/examples/pairs_data/pos010_trap050_tp0001_GFP.png
extraction/examples/pairs_data/pos010_trap050_tp0001_segoutlines.png
extraction/examples/pairs_data/pos010_trap081_tp0001_Brightfield.png
extraction/examples/pairs_data/pos010_trap081_tp0001_GFP.png
extraction/examples/pairs_data/pos010_trap081_tp0001_segoutlines.png
extraction/examples/pos_example.py
extraction/examples/test_pipeline.py
extraction/examples/tiler_error.py
aliby_extraction-0.1.2.dist-info/WHEEL
aliby_extraction-0.1.2.dist-info/METADATA
aliby_extraction-0.1.2.dist-info/RECORD
