Metadata-Version: 2.1
Name: aliby-extraction
Version: 0.1.2
Summary: 
License: GPL-3.0-or-later
Author: Alán Muñoz
Author-email: amuoz@ed.ac.uk
Requires-Python: >=3.7.1,<3.11
Classifier: License :: OSI Approved :: GNU General Public License v3 or later (GPLv3+)
Classifier: Programming Language :: Python :: 3
Classifier: Programming Language :: Python :: 3.10
Classifier: Programming Language :: Python :: 3.8
Classifier: Programming Language :: Python :: 3.9
Requires-Dist: aliby-agora
Requires-Dist: h5py (==2.10)
Requires-Dist: more-itertools (>=8.12.0,<9.0.0)
Requires-Dist: numpy (>=1.17.3)
Requires-Dist: pandas (>=1.3.5,<2.0.0)
Requires-Dist: py-find-1st (>=1.1.5,<2.0.0)
Requires-Dist: scikit-image (>=0.19.1)
Requires-Dist: scikit-learn (==0.22.2.post1)
Requires-Dist: scipy (>=1.4.1)
Requires-Dist: tqdm (>=4.62.3,<5.0.0)
